procyclingstats/__init__.py
procyclingstats/__main__.py
procyclingstats/errors.py
procyclingstats/race_climbs_scraper.py
procyclingstats/race_combative_riders_scraper.py
procyclingstats/race_scraper.py
procyclingstats/race_startlist_scraper.py
procyclingstats/ranking_scraper.py
procyclingstats/rider_results_scraper.py
procyclingstats/rider_scraper.py
procyclingstats/scraper.py
procyclingstats/stage_scraper.py
procyclingstats/table_parser.py
procyclingstats/team_scraper.py
procyclingstats/utils.py
procyclingstats-0.2.7.dist-info/METADATA
procyclingstats-0.2.7.dist-info/WHEEL
procyclingstats-0.2.7.dist-info/top_level.txt
procyclingstats-0.2.7.dist-info/RECORD
