Metadata-Version: 2.4
Name: procyclingstats
Version: 0.2.7
Summary: A Python API wrapper for procyclingstats.com
Home-page: https://github.com/themm1/procyclingstats
Author: Martin Madzin
Author-email: madzin.m@gmail.com
License: MIT
Keywords: cycling cycling-stats procyclingstats scraper html-parsing sports-analytics
Requires-Dist: requests
Requires-Dist: selectolax
Dynamic: author
Dynamic: author-email
Dynamic: description
Dynamic: description-content-type
Dynamic: home-page
Dynamic: keywords
Dynamic: license
Dynamic: requires-dist
Dynamic: summary
